topsis/__init__.py
topsis/topsis.py
topsis_harsaihj_123456-1.0.2.dist-info/licenses/LICENSE
topsis_harsaihj_123456-1.0.2.dist-info/METADATA
topsis_harsaihj_123456-1.0.2.dist-info/WHEEL
topsis_harsaihj_123456-1.0.2.dist-info/entry_points.txt
topsis_harsaihj_123456-1.0.2.dist-info/top_level.txt
topsis_harsaihj_123456-1.0.2.dist-info/RECORD
