Metadata-Version: 2.4
Name: Topsis-Harsaihj-123456
Version: 1.0.2
Summary: TOPSIS package for MCDM problems
Author: Harsaihj Singh
License: MIT
Requires-Python: >=3.6
License-File: LICENSE
Dynamic: author
Dynamic: description
Dynamic: description-content-type
Dynamic: license
Dynamic: license-file
Dynamic: requires-python
Dynamic: summary
